[
	{
		"id" : 1,
		"query" : "INSERT INTO emails_with_events(id, data) VALUES ('6526-d9c2-4980-80b1-25550d90496b', '{'from': 'news_sub@g7g.org', 'to': 'bhaines2@earthlink.net', 'sent': {'date': '2018-12-27 00:00:00.000000', 'timezone_type': 1, 'timezone': '+01:00'}, 'type': 'confirmed', 'events': [{'event_type': 'delivery', 'user_agent': {'browser': None, 'platform': None}, 'position': {'country': None, 'city': None, 'geographical': {'lat': None, 'long': None}}, 'received': {'date': '2018-12-27 00:16:26.000000', 'timezone_type': 1, 'timezone': '+01:00'}, 'occurred': {'date': '2018-12-27 00:00:05.000000', 'timezone_type': 1, 'timezone': '+01:00'}}, {'event_type': 'open', 'user_agent': {'browser': 'Apple Mail', 'platform': 'OS X'}, 'position': {'country': 'US', 'city': 'Arlington', 'geographical': {'lat': 42.4153709412, 'long': -71.1564407349}}, 'received': {'date': '2018-12-27 01:28:24.000000', 'timezone_type': 1, 'timezone': '+01:00'}, 'occurred': {'date': '2018-12-27 00:00:47.000000', 'timezone_type': 1, 'timezone': '+01:00'}}, {'event_type': 'open', 'user_agent': {'browser': 'Chrome', 'platform': 'OS X'}, 'position': {'country': 'US', 'city': 'Arlington', 'geographical': {'lat': 42.4153709412, 'long': -71.1564407349}}, 'received': {'date': '2018-12-27 00:18:22.000000', 'timezone_type': 1, 'timezone': '+01:00'}, 'occurred': {'date': '2018-12-27 00:00:54.000000', 'timezone_type': 1, 'timezone': '+01:00'}}, {'event_type': 'click', 'user_agent': {'browser': 'Chrome', 'platform': 'OS X'}, 'position': {'country': 'US', 'city': 'Arlington', 'geographical': {'lat': 42.4153709412, 'long': -71.1564407349}}, 'received': {'date': '2018-12-27 00:18:22.000000', 'timezone_type': 1, 'timezone': '+01:00'}, 'occurred': {'date': '2018-12-27 00:00:54.000000', 'timezone_type': 1, 'timezone': '+01:00'}}, {'event_type': 'open', 'user_agent': {'browser': 'Apple Mail', 'platform': 'OS X'}, 'position': {'country': 'US', 'city': 'Arlington', 'geographical': {'lat': 42.4153709412, 'long': -71.1564407349}}, 'received': {'date': '2018-12-27 04:07:42.000000', 'timezone_type': 1, 'timezone': '+01:00'}, 'occurred': {'date': '2018-12-27 00:01:55.000000', 'timezone_type': 1, 'timezone': '+01:00'}}, {'event_type': 'open', 'user_agent': {'browser': 'Apple Mail', 'platform': 'OS X'}, 'position': {'country': 'US', 'city': 'Arlington', 'geographical': {'lat': 42.4153709412, 'long': -71.1564407349}}, 'received': {'date': '2018-12-27 01:28:24.000000', 'timezone_type': 1, 'timezone': '+01:00'}, 'occurred': {'date': '2018-12-27 00:01:55.000000', 'timezone_type': 1, 'timezone': '+01:00'}}, {'event_type': 'open', 'user_agent': {'browser': 'Apple Mail', 'platform': 'OS X'}, 'position': {'country': 'US', 'city': 'Arlington', 'geographical': {'lat': 42.4153709412, 'long': -71.1564407349}}, 'received': {'date': '2018-12-27 03:23:24.000000', 'timezone_type': 1, 'timezone': '+01:00'}, 'occurred': {'date': '2018-12-27 00:01:59.000000', 'timezone_type': 1, 'timezone': '+01:00'}}]}')"
	},
	{
		"id" : 2,
		"query" : "SELECT (data -> 'from') as info FROM emails_with_events;"
	},
	{
		"id" : 3,
		"query" : "SELECT (data -> 'from') as info FROM emails_with_events;"
	},
	{
		"id" : 4,
		"query" : "SELECT (data -> 'from') as info FROM emails_with_events;"
	},
	{
		"id" : 5,
		"query" : "SELECT (data -> 'from') as info FROM emails_with_events;"
	},
	{
		"id" : 6,
		"query" : "SELECT (data -> 'from') as info FROM emails_with_events;"
	},
	{
		"id" : 7,
		"query" : "SELECT (data -> 'from') as info FROM emails_with_events;"
	},
	{
		"id" : 8,
		"query" : "SELECT (data -> 'from') as info FROM emails_with_events;"
	},
	{
		"id" : 9,
		"query" : "SELECT (data -> 'from') as info FROM emails_with_events;"
	},
	{
		"id" : 10,
		"query" : "SELECT (data -> 'from') as info FROM emails_with_events;"
	},
	{
		"id" : 11,
		"query" : "SELECT (data -> 'from') as info FROM emails_with_events;"
	},
	{
		"id" : 12,
		"query" : "SELECT (data -> 'from') as info FROM emails_with_events;"
	},
	{
		"id" : 13,
		"query" : "SELECT (data -> 'from') as info FROM emails_with_events;"
	},
	{
		"id" : 14,
		"query" : "SELECT (data -> 'from') as info FROM emails_with_events;"
	}
]